topsis_Abhiraj_102217094/__init__.py
topsis_Abhiraj_102217094/__main__.py
topsis_Abhiraj_102217094/topsis.py
topsis_abhiraj_singh_jhajj_102217094-1.0.6.dist-info/licenses/LICENSE.txt
topsis_abhiraj_singh_jhajj_102217094-1.0.6.dist-info/METADATA
topsis_abhiraj_singh_jhajj_102217094-1.0.6.dist-info/WHEEL
topsis_abhiraj_singh_jhajj_102217094-1.0.6.dist-info/entry_points.txt
topsis_abhiraj_singh_jhajj_102217094-1.0.6.dist-info/top_level.txt
topsis_abhiraj_singh_jhajj_102217094-1.0.6.dist-info/RECORD
